{
  "folder": {
    "id": "123e4567-e89b-12d3-a456-426614174000",
    "name": "Daily English Expressions",
    "createdAt": "2024-01-01T12:00:00.000Z",
    "originalLanguage": "en",
    "translationLanguage": "ko"
  },
  "sentences": [
    {
      "id": 1,
      "order": 1,
      "original": {
        "text": "Little give and go with JaeSung and Sonny. He flicks it over to DongKyung and he back flicks it into the back of the net.",
        "styles": [
          {
            "type": "highlight",
            "start": 7,
            "end": 26
          },
          {
            "type": "bold",
            "start": 27,
            "end": 41
          }
        ]
      },
      "difficulty": "advanced",
      "paraphrases": [
        "JaeSung and Sonny played a quick one-two, then it was passed to DongKyung who flicked it right into the goal."
      ],
      "notes": "flick over: (공을) 가볍게 툭 쳐서 넘기다. 축구 경기 해설에 사용됨.",
      "translation": "이재성과 손흥민 사이에 짧은 패스 주고받기가 있었어요. 이재성이 이동경에게 살짝 넘겨줬고, 이동경은 뒤로 차 넣어 골망을 흔듭니다."
    },
    {
      "id": 3,
      "order": 2,
      "original": {
        "text": "There's a lot of stuff (that) you guys do, that could potentially ruin your trip.",
        "styles": [
          {
            "type": "bold",
            "start": 66,
            "end": 80
          }
        ]
      },
      "difficulty": "intermediate",
      "paraphrases": [
        "There are many things you guys do that might spoil your trip."
      ],
      "notes": "stuff: 것들, 일들 (일반적인 사물이나 일을 지칭)",
      "translation": "너희들이 하는 행동 중에 여행을 망칠 수도 있는 것들이 많아."
    }
  ]
}